odoo/addons/account_invoice_pricelist_technical/README.rst
odoo/addons/account_invoice_pricelist_technical/__init__.py
odoo/addons/account_invoice_pricelist_technical/__manifest__.py
odoo/addons/account_invoice_pricelist_technical/i18n/account_invoice_pricelist_technical.pot
odoo/addons/account_invoice_pricelist_technical/i18n/fr.po
odoo/addons/account_invoice_pricelist_technical/models/__init__.py
odoo/addons/account_invoice_pricelist_technical/models/account_invoice.py
odoo/addons/account_invoice_pricelist_technical/readme/CONTRIBUTORS.rst
odoo/addons/account_invoice_pricelist_technical/readme/DESCRIPTION.rst
odoo/addons/account_invoice_pricelist_technical/static/description/icon.png
odoo/addons/account_invoice_pricelist_technical/static/description/index.html
odoo12_addon_account_invoice_pricelist_technical-12.0.1.0.1.99.dev5.dist-info/METADATA
odoo12_addon_account_invoice_pricelist_technical-12.0.1.0.1.99.dev5.dist-info/WHEEL
odoo12_addon_account_invoice_pricelist_technical-12.0.1.0.1.99.dev5.dist-info/top_level.txt
odoo12_addon_account_invoice_pricelist_technical-12.0.1.0.1.99.dev5.dist-info/RECORD
