Metadata-Version: 2.1
Name: odoo12-addon-account-invoice-pricelist-technical
Version: 12.0.1.0.1.99.dev5
Summary: Prevent technical pricelists from being selected on invoice forms
Home-page: https://github.com/OCA/sale-workflow
Author: GRAP,Odoo Community Association (OCA)
Author-email: support@odoo-community.org
License: AGPL-3
Platform: UNKNOWN
Classifier: Programming Language :: Python
Classifier: Framework :: Odoo
Classifier: Framework :: Odoo :: 12.0
Classifier: License :: OSI Approved :: GNU Affero General Public License v3
Requires-Python: >=3.5
Requires-Dist: odoo12-addon-account-invoice-pricelist
Requires-Dist: odoo12-addon-sale-pricelist-technical
Requires-Dist: odoo <12.1dev,>=12.0a
